README.md
setup.py
PyreeEngine/__init__.py
PyreeEngine/basicObjects.py
PyreeEngine/camera.py
PyreeEngine/engine.py
PyreeEngine/framebuffers.py
PyreeEngine/layers.py
PyreeEngine/log.py
PyreeEngine/objloader.py
PyreeEngine/shaders.py
PyreeEngine/simpleshader.py
PyreeEngine/textures.py
PyreeEngine/util.py
PyreeEngine.egg-info/PKG-INFO
PyreeEngine.egg-info/SOURCES.txt
PyreeEngine.egg-info/dependency_links.txt
PyreeEngine.egg-info/requires.txt
PyreeEngine.egg-info/top_level.txt