Metadata-Version: 1.0
Name: PyreeEngine
Version: 0.1.0
Summary: Pyree Engine
Home-page: https://github.com/DrLuke/PyreeEngine/
Author: Lukas Jackowski
Author-email: Lukas@Jackowski.de
License: MIT License
